{"title":"Body","body":{"content":{"application/json":{"schema":{"properties":{"request_type":{"type":"string","enum":["text","visual","combined"],"title":"Request Type","description":"Type of content to generate","default":"text"},"topics":{"items":{"type":"string"},"type":"array","title":"Topics","description":"Topics for content"},"platform":{"type":"string","enum":["linkedin","twitter","instagram","blog"],"title":"Platform","description":"Target platform","default":"linkedin"},"count":{"type":"integer","maximum":10,"minimum":1,"title":"Count","description":"Pieces per topic","default":1},"tone":{"type":"string","enum":["professional","casual","educational","promotional"],"title":"Tone","description":"Content tone","default":"professional"},"visual_prompt":{"type":"string","title":"Visual Prompt","description":"Image generation prompt","default":""},"visual_style":{"type":"string","enum":["photo","graphic","illustration","logo"],"title":"Visual Style","description":"Visual style","default":"graphic"},"dimensions":{"type":"string","title":"Dimensions","description":"Image dimensions","default":"1080x1080"},"brand_colors":{"anyOf":[{"items":{"type":"string"},"type":"array"},{"type":"null"}],"title":"Brand Colors","description":"Brand colors for visual"}},"type":"object","title":"ContentCreateRequest","description":"Request for unified content creation via Content Director.\n\nSupports text-only, visual-only, or combined generation."}}},"required":true}}