{"title":"Body","body":{"required":true,"content":{"application/json":{"schema":{"properties":{"query":{"type":"string","maxLength":5000,"minLength":3,"title":"Query","description":"Search query text"},"source_table":{"anyOf":[{"type":"string"},{"type":"null"}],"title":"Source Table","description":"Filter by source table (e.g., 'board_meeting_decisions')"},"limit":{"type":"integer","maximum":20,"minimum":1,"title":"Limit","description":"Maximum results to return","default":5},"min_similarity":{"type":"number","maximum":1,"minimum":0,"title":"Min Similarity","description":"Minimum similarity threshold","default":0.5}},"type":"object","required":["query"],"title":"VectorSearchRequest","description":"Request model for vector search."}}}}}